MANIFEST.in
README.rst
setup.cfg
setup.py
psycopg2_range_overlaps/__init__.py
psycopg2_range_overlaps.egg-info/PKG-INFO
psycopg2_range_overlaps.egg-info/SOURCES.txt
psycopg2_range_overlaps.egg-info/dependency_links.txt
psycopg2_range_overlaps.egg-info/requires.txt
psycopg2_range_overlaps.egg-info/top_level.txt