Metadata-Version: 1.1
Name: psycopg2-range-overlaps
Version: 1.0.1
Summary: Use & and = on psycopg2 range types.
Home-page: https://bitbucket.org/schinckel/psycopg2-range-overlaps
Author: Matthew Schinckel
Author-email: matt@schinckel.net
License: UNKNOWN
Platform: UNKNOWN
Classifier: Development Status :: 4 - Beta
Classifier: Intended Audience :: Developers
Classifier: License :: OSI Approved :: BSD License
Classifier: Operating System :: OS Independent
Classifier: Programming Language :: Python :: 2.7
Classifier: Programming Language :: Python :: 3.3
Classifier: Programming Language :: Python :: 3.4
Classifier: Programming Language :: Python :: 3.5
Classifier: Programming Language :: Python :: Implementation :: CPython
Classifier: Programming Language :: Python :: Implementation :: PyPy
Classifier: Topic :: Software Development :: Libraries :: Python Modules
